MANIFEST.in
Makefile
README.md
setup.py
ffcache/__init__.py
ffcache/helper.py
ffcache.egg-info/PKG-INFO
ffcache.egg-info/SOURCES.txt
ffcache.egg-info/dependency_links.txt
ffcache.egg-info/requires.txt
ffcache.egg-info/top_level.txt
src/ffcache.cpp
src/ffcache.hpp
src/ffcacheentry.cpp
src/ffcacheindex.cpp
src/httpheader.cpp
src/main.cpp
src/pymain.cpp
src/structs.cpp
src/util.cpp
src/util.hpp