Metadata-Version: 2.1
Name: ffcache
Version: 0.0.14
Summary: Firefox cache extractor
Home-page: https://github.com/shosatojp/ffcache
Author: shosatojp
Author-email: me@shosato.jp
License: UNKNOWN
Platform: UNKNOWN
Classifier: Programming Language :: Python :: 3
Classifier: License :: OSI Approved :: MIT License
Classifier: Operating System :: OS Independent
Requires-Python: >=3.6
